ascentrade_client/__init__.py
ascentrade_client/all_security_tickers.py
ascentrade_client/async_base_client_open_telemetry.py
ascentrade_client/base_model.py
ascentrade_client/bigint_scalar.py
ascentrade_client/client.py
ascentrade_client/currencies.py
ascentrade_client/currency.py
ascentrade_client/date_scalar.py
ascentrade_client/datetime_scalar.py
ascentrade_client/decimal_scalar.py
ascentrade_client/enums.py
ascentrade_client/exceptions.py
ascentrade_client/exchanges.py
ascentrade_client/input_types.py
ascentrade_client/json_scalar.py
ascentrade_client/ping.py
ascentrade_client/search_security.py
ascentrade_client/security.py
ascentrade_client/start_calculations.py
ascentrade_client/time_scalar.py
ascentrade_client/update_dividends.py
ascentrade_client/update_outstanding_shares.py
ascentrade_client/update_security.py
ascentrade_client/update_security_quotes.py
ascentrade_client/update_splits.py
tests/test.py
ascentrade_client-0.1.1.dist-info/METADATA
ascentrade_client-0.1.1.dist-info/WHEEL
ascentrade_client-0.1.1.dist-info/licenses/LICENSE
ascentrade_client-0.1.1.dist-info/RECORD
