Metadata-Version: 2.4
Name: ascentrade_client
Version: 0.1.1
Summary: API client for the Ascentrade backend
Project-URL: Homepage, https://ascentrade.app
Project-URL: Repository, https://github.com/Ascentrade/ascentrade-client
Project-URL: Issues, https://github.com/Ascentrade/ascentrade-client/issues
Author-email: Dennis Greguhn <dev@greguhn.de>, Pascal Dengler <dev@dengconsult.systems>
License: GNU AFFERO GENERAL PUBLIC LICENSE
License-File: LICENSE
Keywords: financial,graphql,stocks
Classifier: License :: OSI Approved :: GNU Affero General Public License v3 or later (AGPLv3+)
Classifier: Operating System :: OS Independent
Classifier: Programming Language :: Python :: 3
Requires-Python: >=3.10
